<?xml version="1.0"?>
<Scheme Name="Без названия" Tab="Прочее" Descr="" Preview="schemes//preview//" Solver="ode1" StepsForUpdate="50" ModelingTime="715" ModelingStep="0.1" HydraulicAccuracy="0.1" HydroComponents="" HydroMass="">
    <ExtData/>
    <Blocks>
        <Block ID="0" x="1784" y="1390" Name_x="-58.5" Name_y="53" BlockType="GCS_AeroFilter" BlockName="Аэрозольный фильтр" Image="library//images//aerofilter.png">
            <Parameters>
                <Parameter Code="filterCrossSectionalArea" Name="Площадь поперечного сечения, м^2" Value="0.01" Tab="Параметры" Visible="true"/>
                <Parameter Code="filterCatchCoef" Name="Коэффициент улавливания фильтра" Value="0.4" Tab="Параметры" Visible="true"/>
                <Parameter Code="filterPressureLossCoef" Name="Коэффициент перепада давления из-за осаждения частиц, устанавливается экспериментально Па/кг" Value="1000" Tab="Параметры" Visible="true"/>
                <Parameter Code="filterFiberLength" Name="Длина волокон, приходящихся на единицу площади фильтрующего материала, м-1" Value="10" Tab="Параметры" Visible="true"/>
                <Parameter Code="filterResistanceForce" Name="Безразмерная сила сопротивления, действующая на единицу длины волокна" Value="20" Tab="Параметры" Visible="true"/>
                <Parameter Code="filterInitMassParticle" Name="Начальная масса частиц на фильтре, кг" Value="0" Tab="Параметры" Visible="true"/>
                <Parameter Code="maxParticleMass" Name="Максимальная масса частиц на фильтре, кг" Value="50" Tab="Параметры" Visible="true"/>
                <Parameter Code="filterVolume" Name="Внутренний объем фильтра, м^3" Value="1" Tab="Параметры" Visible="true"/>
                <Parameter Code="timeFilterBreak" Name="Время прорыва фильтра, с" Value="50" Tab="Настройки аварий" Visible="true"/>
            </Parameters>
            <Signals/>
            <Ports>
                <Port Input="true" Type="INFO" Dir="R" ToolTip="Входной газовый поток" x="-8" y="15.5"/>
                <Port Input="false" Type="INFO" Dir="R" ToolTip="Выходной газовый поток" x="58" y="15.5"/>
                <Port Input="false" Type="INFO" Dir="U" ToolTip="Выходные парметры фильтра" x="24" y="-7.5"/>
                <Port Input="true" Type="INFO" Dir="L" ToolTip="Входной коэффициент сопротивления (от 0 до 1)" x="58" y="39"/>
                <Port Input="false" Type="INFO" Dir="L" ToolTip="Выходной коэффициент сопротивления (от 0 до 1)" x="-9" y="39"/>
            </Ports>
            <Situations>
                <Situation Code="filterBreak" Name="Прорыв фильтра" Tab="Отказы"/>
                <Situation Code="filterClog" Name="Забивка фильтра" Tab="Отказы"/>
            </Situations>
            <ExtData/>
        </Block>
        <Block ID="1" x="1559" y="1373" Name_x="-60" Name_y="53" BlockType="GCS_SourceBlock" BlockName="Источник газа (насос)" Image="library//images//pump.png">
            <Parameters>
                <Parameter Code="gasFlowRate" Name="Объемный расход газа, м^3/с" Value="0.026" Tab="Параметры" Visible="true"/>
                <Parameter Code="gasPressure" Name="Заданное давление газа, Па" Value="100000" Tab="Параметры" Visible="true"/>
                <Parameter Code="gasTemperature" Name="Температура газа, °C" Value="500" Tab="Параметры" Visible="true"/>
                <Parameter Code="gasActivity" Name="Объемная активность газа, Бк/м^3" Value="10000" Tab="Параметры" Visible="true"/>
                <Parameter Code="particleFraction" Name="Объемная доля частиц в газе, отн. ед." Value="0.005" Tab="Параметры" Visible="true"/>
                <Parameter Code="pumpMaxPressure" Name="Макс. давление насоса, Па" Value="300000" Tab="Параметры" Visible="true"/>
            </Parameters>
            <Signals/>
            <Ports>
                <Port Input="false" Type="INFO" Dir="R" ToolTip="Выходной поток газа" x="59" y="15"/>
                <Port Input="true" Type="INFO" Dir="L" ToolTip="Входной коэффициент сопротивления (от 0 до 1)" x="58" y="37"/>
            </Ports>
            <ExtData/>
        </Block>
        <Block ID="2" x="1733" y="1546" Name_x="-17" Name_y="53" BlockType="Const" BlockName="Константа" Image="library//images//const.png">
            <Parameters>
                <Parameter Code="CONST_VAL" Name="Значение" Value="0" Tab="" Visible="true"/>
            </Parameters>
            <Signals>
                <Signal Code="ConstValue" Name="Константа" Type="double"/>
            </Signals>
            <Ports>
                <Port Input="false" Type="INFO" Dir="R" ToolTip="Выходной" x="57" y="27"/>
            </Ports>
            <Visual_Signals>
                <Visual_signal Type="Value" Code="ConstValue" Height="10" Width="10" Quantity="5" SizeFont="10" Unit=" " x="10" y="30"/>
            </Visual_Signals>
            <ExtData/>
        </Block>
        <Block ID="3" x="1968" y="1220" Name_x="-18.5" Name_y="52" BlockType="Chart" BlockName="Самописец" Image="">
            <Parameters/>
            <Signals/>
            <Ports>
                <Port Input="true" Type="INFO" Dir="R" ToolTip="" x="-6" y="19"/>
            </Ports>
            <ExtData/>
        </Block>
        <Block ID="4" x="2114" y="1397" Name_x="-18.5" Name_y="52" BlockType="Chart" BlockName="Самописец" Image="">
            <Parameters/>
            <Signals/>
            <Ports>
                <Port Input="true" Type="INFO" Dir="R" ToolTip="" x="-6" y="19"/>
            </Ports>
            <ExtData/>
        </Block>
        <Block ID="5" x="1571" y="1726" Name_x="35" Name_y="30" BlockType="Indicator" BlockName="" Image="">
            <Parameters>
                <Parameter Code="SIZE" Name="Размер вектора" Value="1" Tab="" Visible="true"/>
                <Parameter Code="SIGNS" Name="Количество значащих цифр" Value="3" Tab="" Visible="true"/>
                <Parameter Code="FORMAT" Name="Экспоненциальный формат вывода чисел" Value="0" Tab="" Visible="true"/>
                <Parameter Code="SENSTOP" Name="Верхняя граница чувствительности" Value="0" Tab="" Visible="true"/>
                <Parameter Code="SENSBOT" Name="Нижняя граница чувствительности" Value="0" Tab="" Visible="true"/>
            </Parameters>
            <Signals/>
            <Ports>
                <Port Input="true" Type="INFO" Dir="R" ToolTip="" x="-8" y="14"/>
            </Ports>
            <ExtData/>
        </Block>
    </Blocks>
    <Links>
        <Link>
            <Begin Object="Port" Block="0" Port="4"/>
            <End Object="Node" ID="0"/>
            <Source Block="0" Port="4"/>
            <Points>
                <Point x="1775" y="1429"/>
                <Point x="1760" y="1429"/>
                <Point x="1696" y="1429"/>
                <Point x="1696" y="1427"/>
            </Points>
        </Link>
        <Link>
            <Begin Object="Port" Block="2" Port="0"/>
            <End Object="Port" Block="0" Port="3"/>
            <Source Block="2" Port="0"/>
            <Points>
                <Point x="1790" y="1573"/>
                <Point x="1805" y="1573"/>
                <Point x="1857" y="1573"/>
                <Point x="1857" y="1429"/>
                <Point x="1842" y="1429"/>
            </Points>
        </Link>
        <Link>
            <Begin Object="Port" Block="1" Port="0"/>
            <End Object="Port" Block="0" Port="0"/>
            <Source Block="1" Port="0"/>
            <Points>
                <Point x="1618" y="1388"/>
                <Point x="1633" y="1388"/>
                <Point x="1697" y="1388"/>
                <Point x="1697" y="1405.5"/>
                <Point x="1761" y="1405.5"/>
                <Point x="1776" y="1405.5"/>
            </Points>
        </Link>
        <Link>
            <Begin Object="Port" Block="0" Port="1"/>
            <End Object="Port" Block="4" Port="0"/>
            <Source Block="0" Port="1"/>
            <Points>
                <Point x="1842" y="1405.5"/>
                <Point x="1857" y="1405.5"/>
                <Point x="1975" y="1405.5"/>
                <Point x="1975" y="1416"/>
                <Point x="2093" y="1416"/>
                <Point x="2108" y="1416"/>
            </Points>
        </Link>
        <Link>
            <Begin Object="Port" Block="0" Port="2"/>
            <End Object="Port" Block="3" Port="0"/>
            <Source Block="0" Port="2"/>
            <Points>
                <Point x="1808" y="1382.5"/>
                <Point x="1808" y="1367.5"/>
                <Point x="1808" y="1239"/>
                <Point x="1947" y="1239"/>
                <Point x="1962" y="1239"/>
            </Points>
        </Link>
        <Link>
            <Begin Object="Node" ID="0"/>
            <End Object="Port" Block="1" Port="1"/>
            <Source Block="0" Port="4"/>
            <Points>
                <Point x="1696" y="1427"/>
                <Point x="1696" y="1410"/>
                <Point x="1632" y="1410"/>
                <Point x="1617" y="1410"/>
            </Points>
        </Link>
        <Link>
            <Begin Object="Node" ID="0"/>
            <End Object="Port" Block="5" Port="0"/>
            <Source Block="0" Port="4"/>
            <Points>
                <Point x="1696" y="1427"/>
                <Point x="1548" y="1427"/>
                <Point x="1548" y="1740"/>
                <Point x="1563" y="1740"/>
            </Points>
        </Link>
    </Links>
    <Labels/>
</Scheme>
